{
    "r_prec": {
        "AlsaceRegion": 1.0,
        "AnjouRegion": 1.0,
        "ArroyoGrandeRegion": 1.0,
        "AustralianRegion": 1.0,
        "BancroftChardonnay": 1.0,
        "Beringer": 1.0,
        "BourgogneRegion": 1.0,
        "CaliforniaRegion": 1.0,
        "CentralCoastRegion": 1.0,
        "CentralTexasRegion": 1.0,
        "ChateauDYchem": 1.0,
        "ChateauMorgonBeaujolais": 1.0,
        "ClosDeLaPoussie": 1.0,
        "ClosDeLaPoussieSancerre": 1.0,
        "CorbansPrivateBinSauvignonBlanc": 1.0,
        "CortonMontrachetWhiteBurgundy": 1.0,
        "CotesDOrRegion": 1.0,
        "CotturiZinfandel": 1.0,
        "EdnaValleyRegion": 1.0,
        "ElyseZinfandel": 1.0,
        "GermanyRegion": 1.0,
        "Handley": 1.0,
        "KalinCellars": 1.0,
        "KalinCellarsSemillon": 1.0,
        "LaneTannerPinotNoir": 1.0,
        "LoireRegion": 1.0,
        "LongridgeMerlot": 1.0,
        "Marietta": 1.0,
        "MariettaPetiteSyrah": 1.0,
        "MariettaZinfandel": 1.0,
        "MendocinoRegion": 1.0,
        "MeursaultRegion": 1.0,
        "MountEdenVineyard": 1.0,
        "MountadamChardonnay": 1.0,
        "NewZealandRegion": 1.0,
        "PageMillWinery": 1.0,
        "PageMillWineryCabernetSauvignon": 1.0,
        "PauillacRegion": 1.0,
        "PeterMccoyChardonnay": 1.0,
        "PinotBlancGrape": 1.0,
        "PulignyMontrachetWhiteBurgundy": 1.0,
        "SantaBarbaraRegion": 1.0,
        "SantaCruzMountainVineyardCabernetSauvignon": 1.0,
        "SantaCruzMountainsRegion": 1.0,
        "SaucelitoCanyon": 1.0,
        "SaucelitoCanyonZinfandel": 1.0,
        "SaucelitoCanyonZinfandel1998": 1.0,
        "SchlossRothermel": 1.0,
        "SelaksIceWine": 1.0,
        "SelaksSauvignonBlanc": 1.0,
        "SevreEtMaineMuscadet": 1.0,
        "SouthAustraliaRegion": 1.0,
        "Strong": 1.0,
        "TaylorPort": 1.0,
        "TexasRegion": 1.0,
        "USRegion": 1.0,
        "Ventana": 1.0,
        "Year1998": 1.0,
        "Delicate": 0.6666666666666666,
        "Medium": 0.6666666666666666,
        "CabernetFrancGrape": 0.5,
        "ChardonnayGrape": 0.5,
        "CheninBlancGrape": 0.5,
        "ChiantiClassico": 0.5,
        "GamayGrape": 0.5,
        "MalbecGrape": 0.5,
        "MerlotGrape": 0.5,
        "PetiteSyrahGrape": 0.5,
        "PinotNoirGrape": 0.5,
        "RieslingGrape": 0.5,
        "Rose": 0.5,
        "SangioveseGrape": 0.5,
        "SauvignonBlancGrape": 0.5,
        "SemillonGrape": 0.5,
        "ZinfandelGrape": 0.5,
        "ChateauDYchemSauterne": 0.4,
        "Light": 0.3333333333333333,
        "SchlossVolradTrochenbierenausleseRiesling": 0.25,
        "Bancroft": 0.0,
        "BeaujolaisRegion": 0.0,
        "BordeauxRegion": 0.0,
        "CabernetSauvignonGrape": 0.0,
        "ChateauChevalBlanc": 0.0,
        "ChateauChevalBlancStEmilion": 0.0,
        "ChateauDeMeursault": 0.0,
        "ChateauDeMeursaultMeursault": 0.0,
        "ChateauLafiteRothschild": 0.0,
        "ChateauLafiteRothschildPauillac": 0.0,
        "ChateauMargaux": 0.0,
        "ChateauMargauxWinery": 0.0,
        "ChateauMorgon": 0.0,
        "ChiantiRegion": 0.0,
        "ClosDeVougeot": 0.0,
        "ClosDeVougeotCotesDOr": 0.0,
        "CongressSprings": 0.0,
        "CongressSpringsSemillon": 0.0,
        "Corbans": 0.0,
        "CorbansDryWhiteRiesling": 0.0,
        "CorbansSauvignonBlanc": 0.0,
        "CortonMontrachet": 0.0,
        "Cotturi": 0.0,
        "DAnjou": 0.0,
        "Dry": 0.0,
        "Elyse": 0.0,
        "Forman": 0.0,
        "FormanCabernetSauvignon": 0.0,
        "FormanChardonnay": 0.0,
        "Foxen": 0.0,
        "FoxenCheninBlanc": 0.0,
        "FrenchRegion": 0.0,
        "Full": 0.0,
        "GaryFarrell": 0.0,
        "GaryFarrellMerlot": 0.0,
        "ItalianRegion": 0.0,
        "KathrynKennedy": 0.0,
        "KathrynKennedyLateral": 0.0,
        "LaneTanner": 0.0,
        "Longridge": 0.0,
        "MargauxRegion": 0.0,
        "MariettaCabernetSauvignon": 0.0,
        "MariettaOldVinesRed": 0.0,
        "McGuinnesso": 0.0,
        "MedocRegion": 0.0,
        "Moderate": 0.0,
        "MountEdenVineyardEdnaValleyChardonnay": 0.0,
        "MountEdenVineyardEstatePinotNoir": 0.0,
        "Mountadam": 0.0,
        "MountadamPinotNoir": 0.0,
        "MountadamRiesling": 0.0,
        "MuscadetRegion": 0.0,
        "NapaRegion": 0.0,
        "OffDry": 0.0,
        "PeterMccoy": 0.0,
        "PetiteVerdotGrape": 0.0,
        "PortugalRegion": 0.0,
        "PulignyMontrachet": 0.0,
        "Red": 0.0,
        "RoseDAnjou": 0.0,
        "SancerreRegion": 0.0,
        "SantaCruzMountainVineyard": 0.0,
        "SauterneRegion": 0.0,
        "SchlossRothermelTrochenbierenausleseRiesling": 0.0,
        "SchlossVolrad": 0.0,
        "SeanThackrey": 0.0,
        "SeanThackreySiriusPetiteSyrah": 0.0,
        "Selaks": 0.0,
        "SevreEtMaine": 0.0,
        "SonomaRegion": 0.0,
        "StEmilionRegion": 0.0,
        "StGenevieve": 0.0,
        "StGenevieveTexasWhite": 0.0,
        "Stonleigh": 0.0,
        "StonleighSauvignonBlanc": 0.0,
        "Sweet": 0.0,
        "Taylor": 0.0,
        "ToursRegion": 0.0,
        "VentanaCheninBlanc": 0.0,
        "White": 0.0,
        "WhitehallLane": 0.0,
        "WhitehallLaneCabernetFranc": 0.0,
        "WhitehallLanePrimavera": 0.0
    },
    "macro_r_prec": 0.4212215320910973,
    "ap_k": {
        "AlsaceRegion": 1.0,
        "AnjouRegion": 1.0,
        "ArroyoGrandeRegion": 1.0,
        "AustralianRegion": 1.0,
        "BancroftChardonnay": 1.0,
        "Beringer": 1.0,
        "BourgogneRegion": 1.0,
        "CaliforniaRegion": 1.0,
        "CentralCoastRegion": 1.0,
        "CentralTexasRegion": 1.0,
        "ChateauDYchem": 1.0,
        "ChateauMorgonBeaujolais": 1.0,
        "ClosDeLaPoussie": 1.0,
        "ClosDeLaPoussieSancerre": 1.0,
        "CorbansPrivateBinSauvignonBlanc": 1.0,
        "CortonMontrachetWhiteBurgundy": 1.0,
        "CotesDOrRegion": 1.0,
        "CotturiZinfandel": 1.0,
        "EdnaValleyRegion": 1.0,
        "ElyseZinfandel": 1.0,
        "GermanyRegion": 1.0,
        "Handley": 1.0,
        "KalinCellars": 1.0,
        "KalinCellarsSemillon": 1.0,
        "LaneTannerPinotNoir": 1.0,
        "LoireRegion": 1.0,
        "LongridgeMerlot": 1.0,
        "Marietta": 1.0,
        "MariettaPetiteSyrah": 1.0,
        "MariettaZinfandel": 1.0,
        "MendocinoRegion": 1.0,
        "MeursaultRegion": 1.0,
        "MountEdenVineyard": 1.0,
        "MountadamChardonnay": 1.0,
        "NewZealandRegion": 1.0,
        "PageMillWinery": 1.0,
        "PageMillWineryCabernetSauvignon": 1.0,
        "PauillacRegion": 1.0,
        "PeterMccoyChardonnay": 1.0,
        "PinotBlancGrape": 1.0,
        "PulignyMontrachetWhiteBurgundy": 1.0,
        "SantaBarbaraRegion": 1.0,
        "SantaCruzMountainVineyardCabernetSauvignon": 1.0,
        "SantaCruzMountainsRegion": 1.0,
        "SaucelitoCanyon": 1.0,
        "SaucelitoCanyonZinfandel": 1.0,
        "SaucelitoCanyonZinfandel1998": 1.0,
        "SchlossRothermel": 1.0,
        "SelaksIceWine": 1.0,
        "SelaksSauvignonBlanc": 1.0,
        "SevreEtMaineMuscadet": 1.0,
        "SouthAustraliaRegion": 1.0,
        "Strong": 1.0,
        "TaylorPort": 1.0,
        "TexasRegion": 1.0,
        "USRegion": 1.0,
        "Ventana": 1.0,
        "Year1998": 1.0,
        "MalbecGrape": 0.8333333333333333,
        "Medium": 0.8055555555555555,
        "Delicate": 0.6666666666666666,
        "BeaujolaisRegion": 0.5,
        "CabernetFrancGrape": 0.5,
        "ChateauMargauxWinery": 0.5,
        "CheninBlancGrape": 0.5,
        "ChiantiRegion": 0.5,
        "CongressSpringsSemillon": 0.5,
        "FormanChardonnay": 0.5,
        "GamayGrape": 0.5,
        "GaryFarrellMerlot": 0.5,
        "MargauxRegion": 0.5,
        "MedocRegion": 0.5,
        "MuscadetRegion": 0.5,
        "PinotNoirGrape": 0.5,
        "PortugalRegion": 0.5,
        "SancerreRegion": 0.5,
        "SangioveseGrape": 0.5,
        "SantaCruzMountainVineyard": 0.5,
        "SauterneRegion": 0.5,
        "SeanThackreySiriusPetiteSyrah": 0.5,
        "StGenevieveTexasWhite": 0.5,
        "Taylor": 0.5,
        "WhitehallLaneCabernetFranc": 0.5,
        "ZinfandelGrape": 0.5,
        "ChateauDYchemSauterne": 0.41666666666666663,
        "Light": 0.3333333333333333,
        "MariettaCabernetSauvignon": 0.3333333333333333,
        "ChardonnayGrape": 0.25,
        "ChateauMorgon": 0.25,
        "ChiantiClassico": 0.25,
        "FoxenCheninBlanc": 0.25,
        "KathrynKennedy": 0.25,
        "MerlotGrape": 0.25,
        "MountadamRiesling": 0.25,
        "PetiteSyrahGrape": 0.25,
        "RieslingGrape": 0.25,
        "Rose": 0.25,
        "SauvignonBlancGrape": 0.25,
        "SemillonGrape": 0.25,
        "SonomaRegion": 0.25,
        "CabernetSauvignonGrape": 0.125,
        "PetiteVerdotGrape": 0.125,
        "SchlossVolradTrochenbierenausleseRiesling": 0.125,
        "White": 0.125,
        "Moderate": 0.08333333333333333,
        "WhitehallLanePrimavera": 0.08333333333333333,
        "Bancroft": 0.0,
        "BordeauxRegion": 0.0,
        "ChateauChevalBlanc": 0.0,
        "ChateauChevalBlancStEmilion": 0.0,
        "ChateauDeMeursault": 0.0,
        "ChateauDeMeursaultMeursault": 0.0,
        "ChateauLafiteRothschild": 0.0,
        "ChateauLafiteRothschildPauillac": 0.0,
        "ChateauMargaux": 0.0,
        "ClosDeVougeot": 0.0,
        "ClosDeVougeotCotesDOr": 0.0,
        "CongressSprings": 0.0,
        "Corbans": 0.0,
        "CorbansDryWhiteRiesling": 0.0,
        "CorbansSauvignonBlanc": 0.0,
        "CortonMontrachet": 0.0,
        "Cotturi": 0.0,
        "DAnjou": 0.0,
        "Dry": 0.0,
        "Elyse": 0.0,
        "Forman": 0.0,
        "FormanCabernetSauvignon": 0.0,
        "Foxen": 0.0,
        "FrenchRegion": 0.0,
        "Full": 0.0,
        "GaryFarrell": 0.0,
        "ItalianRegion": 0.0,
        "KathrynKennedyLateral": 0.0,
        "LaneTanner": 0.0,
        "Longridge": 0.0,
        "MariettaOldVinesRed": 0.0,
        "McGuinnesso": 0.0,
        "MountEdenVineyardEdnaValleyChardonnay": 0.0,
        "MountEdenVineyardEstatePinotNoir": 0.0,
        "Mountadam": 0.0,
        "MountadamPinotNoir": 0.0,
        "NapaRegion": 0.0,
        "OffDry": 0.0,
        "PeterMccoy": 0.0,
        "PulignyMontrachet": 0.0,
        "Red": 0.0,
        "RoseDAnjou": 0.0,
        "SchlossRothermelTrochenbierenausleseRiesling": 0.0,
        "SchlossVolrad": 0.0,
        "SeanThackrey": 0.0,
        "Selaks": 0.0,
        "SevreEtMaine": 0.0,
        "StEmilionRegion": 0.0,
        "StGenevieve": 0.0,
        "Stonleigh": 0.0,
        "StonleighSauvignonBlanc": 0.0,
        "Sweet": 0.0,
        "ToursRegion": 0.0,
        "VentanaCheninBlanc": 0.0,
        "WhitehallLane": 0.0
    },
    "map_4": 0.47705314009661837,
    "map_1": 0.42857142857142855,
    "ndcg_4": 0.42602091904107053
}