{"Individual":"AlsaceRegion","Response":"1. Region","Prediction":["Region"]}
{"Individual":"AnjouRegion","Response":"1. Region\n2. Anjou","Prediction":["Region","Anjou"]}
{"Individual":"ArroyoGrandeRegion","Response":"1. Region","Prediction":["Region"]}
{"Individual":"AustralianRegion","Response":"1. Region","Prediction":["Region"]}
{"Individual":"Bancroft","Response":"1. Winery","Prediction":["Winery"]}
{"Individual":"BancroftChardonnay","Response":"1. Chardonnay\n2. Wine","Prediction":["Chardonnay","Wine"]}
{"Individual":"BeaujolaisRegion","Response":"1. Region\n2. Beaujolais","Prediction":["Region","Beaujolais"]}
{"Individual":"Beringer","Response":"1. Winery\n2. Wine","Prediction":["Winery","Wine"]}
{"Individual":"BordeauxRegion","Response":"1. Region","Prediction":["Region"]}
{"Individual":"BourgogneRegion","Response":"1. Region\n2. Bordeaux","Prediction":["Region","Bordeaux"]}
{"Individual":"CabernetFrancGrape","Response":"1. WineGrape\n2. Grape","Prediction":["WineGrape","Grape"]}
{"Individual":"CabernetSauvignonGrape","Response":"1. WineGrape\n2. Grape","Prediction":["WineGrape","Grape"]}
{"Individual":"CaliforniaRegion","Response":"1. Region","Prediction":["Region"]}
{"Individual":"CentralCoastRegion","Response":"1. Region","Prediction":["Region"]}
{"Individual":"CentralTexasRegion","Response":"1. Region","Prediction":["Region"]}
{"Individual":"ChardonnayGrape","Response":"1. WineGrape\n2. Grape","Prediction":["WineGrape","Grape"]}
{"Individual":"ChateauChevalBlanc","Response":"1. Bordeaux\n2. Margaux\n3. Pauillac","Prediction":["Bordeaux","Margaux","Pauillac"]}
{"Individual":"ChateauChevalBlancStEmilion","Response":"1. StEmilion\n2. Region\n3. Wine\n4. Bordeaux","Prediction":["StEmilion","Region","Wine","Bordeaux"]}
{"Individual":"ChateauDYchem","Response":"1. Bordeaux\n2. Region\n3. Winery\n4. Wine","Prediction":["Bordeaux","Region","Winery","Wine"]}
{"Individual":"ChateauDYchemSauterne","Response":"1. Sauternes\n2. DessertWine\n3. Wine\n4. Bordeaux","Prediction":["Sauternes","DessertWine","Wine","Bordeaux"]}
{"Individual":"ChateauDeMeursault","Response":"1. Meursault\n2. Wine\n3. Bordeaux\n4. Chateau","Prediction":["Meursault","Wine","Bordeaux","Chateau"]}
{"Individual":"ChateauDeMeursaultMeursault","Response":"1. Meursault\n2. WhiteBurgundy","Prediction":["Meursault","WhiteBurgundy"]}
{"Individual":"ChateauLafiteRothschild","Response":"1. Bordeaux\n2. Meritage\n3. CabernetSauvignon\n4. RedWine","Prediction":["Bordeaux","Meritage","CabernetSauvignon","RedWine"]}
{"Individual":"ChateauLafiteRothschildPauillac","Response":"1. Bordeaux\n2. Pauillac\n3. Margaux","Prediction":["Bordeaux","Pauillac","Margaux"]}
{"Individual":"ChateauMargaux","Response":"1. Bordeaux\n2. Margaux","Prediction":["Bordeaux","Margaux"]}
{"Individual":"ChateauMargauxWinery","Response":"1. Winery\n2. Bordeaux","Prediction":["Winery","Bordeaux"]}
{"Individual":"ChateauMorgon","Response":"1. Bordeaux\n2. Chateau\n3. Region","Prediction":["Bordeaux","Chateau","Region"]}
{"Individual":"ChateauMorgonBeaujolais","Response":"1. Beaujolais\n2. Wine","Prediction":["Beaujolais","Wine"]}
{"Individual":"CheninBlancGrape","Response":"1. WineGrape\n2. Grape","Prediction":["WineGrape","Grape"]}
{"Individual":"ChiantiClassico","Response":"1. Chianti\n2. ItalianWine","Prediction":["Chianti","ItalianWine"]}
{"Individual":"ChiantiRegion","Response":"1. Region\n2. Chianti","Prediction":["Region","Chianti"]}
{"Individual":"ClosDeLaPoussie","Response":"1. Bordeaux\n2. Region\n3. CotesDOr\n4. Wine","Prediction":["Bordeaux","Region","CotesDOr","Wine"]}
{"Individual":"ClosDeLaPoussieSancerre","Response":"1. Sancerre\n2. Region","Prediction":["Sancerre","Region"]}
{"Individual":"ClosDeVougeot","Response":"1. CotesDOr\n2. Region","Prediction":["CotesDOr","Region"]}
{"Individual":"ClosDeVougeotCotesDOr","Response":"1. CotesDOr\n2. Region","Prediction":["CotesDOr","Region"]}
{"Individual":"CongressSprings","Response":"1. Winery","Prediction":["Winery"]}
{"Individual":"CongressSpringsSemillon","Response":"1. Semillon\n2. WineGrape\n3. Grape\n4. Wine","Prediction":["Semillon","WineGrape","Grape","Wine"]}
{"Individual":"Corbans","Response":"1. Bordeaux\n2. Meritage\n3. Wine\n4. CabernetFranc","Prediction":["Bordeaux","Meritage","Wine","CabernetFranc"]}
{"Individual":"CorbansDryWhiteRiesling","Response":"1. DryRiesling\n2. Wine\n3. WhiteWine","Prediction":["DryRiesling","Wine","WhiteWine"]}
{"Individual":"CorbansPrivateBinSauvignonBlanc","Response":"1. SauvignonBlanc\n2. WhiteWine\n3. Wine\n4. PotableLiquid","Prediction":["SauvignonBlanc","WhiteWine","Wine","PotableLiquid"]}
{"Individual":"CorbansSauvignonBlanc","Response":"1. Wine\n2. SauvignonBlanc\n3. WineGrape\n4. Grape","Prediction":["Wine","SauvignonBlanc","WineGrape","Grape"]}
{"Individual":"CortonMontrachet","Response":"1. Meursault\n2. WhiteBurgundy","Prediction":["Meursault","WhiteBurgundy"]}
{"Individual":"CortonMontrachetWhiteBurgundy","Response":"1. WhiteBurgundy\n2. Wine","Prediction":["WhiteBurgundy","Wine"]}
{"Individual":"CotesDOrRegion","Response":"1. Region\n2. CotesDOr","Prediction":["Region","CotesDOr"]}
{"Individual":"Cotturi","Response":"1. CotesDOr","Prediction":["CotesDOr"]}
{"Individual":"CotturiZinfandel","Response":"1. Zinfandel\n2. Wine\n3. Grape","Prediction":["Zinfandel","Wine","Grape"]}
{"Individual":"DAnjou","Response":"1. Anjou\n2. Wine","Prediction":["Anjou","Wine"]}
{"Individual":"Delicate","Response":"1. WineFlavor\n2. WineDescriptor","Prediction":["WineFlavor","WineDescriptor"]}
{"Individual":"Dry","Response":"1. Wine\n2. WineBody\n3. WineFlavor\n4. WineSugar","Prediction":["Wine","WineBody","WineFlavor","WineSugar"]}
{"Individual":"EdnaValleyRegion","Response":"1. Region\n2. EdnaValley","Prediction":["Region","EdnaValley"]}
{"Individual":"Elyse","Response":"1. Wine\n2. Winery","Prediction":["Wine","Winery"]}
{"Individual":"ElyseZinfandel","Response":"1. Zinfandel\n2. Wine","Prediction":["Zinfandel","Wine"]}
{"Individual":"Forman","Response":"1. Merlot\n2. CabernetFranc","Prediction":["Merlot","CabernetFranc"]}
{"Individual":"FormanCabernetSauvignon","Response":"1. CabernetSauvignon\n2. Wine","Prediction":["CabernetSauvignon","Wine"]}
{"Individual":"FormanChardonnay","Response":"1. Chardonnay\n2. Wine","Prediction":["Chardonnay","Wine"]}
{"Individual":"FoxenCheninBlanc","Response":"1. Wine\n2. CheninBlanc\n3. WhiteWine","Prediction":["Wine","CheninBlanc","WhiteWine"]}
{"Individual":"FrenchRegion","Response":"1. Region\n2. Bordeaux","Prediction":["Region","Bordeaux"]}
{"Individual":"Full","Response":"1. Wine\n2. PotableLiquid\n3. Semillon\n4. Grape","Prediction":["Wine","PotableLiquid","Semillon","Grape"]}
{"Individual":"GamayGrape","Response":"1. WineGrape\n2. Grape","Prediction":["WineGrape","Grape"]}
{"Individual":"GaryFarrell","Response":"1. Bordeaux","Prediction":["Bordeaux"]}
{"Individual":"GaryFarrellMerlot","Response":"1. Merlot\n2. CabernetFranc\n3. Grape\n4. Wine","Prediction":["Merlot","CabernetFranc","Grape","Wine"]}
{"Individual":"Handley","Response":"1. Wine\n2. WineBody","Prediction":["Wine","WineBody"]}
{"Individual":"ItalianRegion","Response":"1. Region\n2. Region","Prediction":["Region","Region"]}
{"Individual":"KalinCellars","Response":"1. Winery","Prediction":["Winery"]}
{"Individual":"KalinCellarsSemillon","Response":"1. Meursault\n2. Semillon\n3. Wine\n4. ItalianWine","Prediction":["Meursault","Semillon","Wine","ItalianWine"]}
{"Individual":"KathrynKennedy","Response":"1. Wine\n2. WineDescriptor","Prediction":["Wine","WineDescriptor"]}
{"Individual":"KathrynKennedyLateral","Response":"1. Wine\n2. Region\n3. WineGrape","Prediction":["Wine","Region","WineGrape"]}
{"Individual":"LaneTanner","Response":"1. Winery\n2. WineBody\n3. Wine\n4. PotableLiquid","Prediction":["Winery","WineBody","Wine","PotableLiquid"]}
{"Individual":"LaneTannerPinotNoir","Response":"1. PinotNoir\n2. Wine\n3. RedWine","Prediction":["PinotNoir","Wine","RedWine"]}
{"Individual":"Light","Response":"1. WineBody\n2. Wine\n3. PotableLiquid","Prediction":["WineBody","Wine","PotableLiquid"]}
{"Individual":"LoireRegion","Response":"1. Region","Prediction":["Region"]}
{"Individual":"Longridge","Response":"1. WineBody","Prediction":["WineBody"]}
{"Individual":"LongridgeMerlot","Response":"1. Merlot\n2. Grape\n3. WineGrape\n4. Wine","Prediction":["Merlot","Grape","WineGrape","Wine"]}
{"Individual":"MalbecGrape","Response":"1. WineGrape\n2. Grape","Prediction":["WineGrape","Grape"]}
{"Individual":"MargauxRegion","Response":"1. Region\n2. Bordeaux","Prediction":["Region","Bordeaux"]}
{"Individual":"Marietta","Response":"1. Winery","Prediction":["Winery"]}
{"Individual":"MariettaCabernetSauvignon","Response":"1. CabernetSauvignon\n2. Wine\n3. RedWine\n4. Meritage","Prediction":["CabernetSauvignon","Wine","RedWine","Meritage"]}
{"Individual":"MariettaOldVinesRed","Response":"1. Meritage\n2. RedWine\n3. RedTableWine","Prediction":["Meritage","RedWine","RedTableWine"]}
{"Individual":"MariettaPetiteSyrah","Response":"1. PetiteSyrah\n2. WineGrape\n3. Grape","Prediction":["PetiteSyrah","WineGrape","Grape"]}
{"Individual":"MariettaZinfandel","Response":"1. Zinfandel\n2. RedWine\n3. Wine\n4. Grape","Prediction":["Zinfandel","RedWine","Wine","Grape"]}
{"Individual":"McGuinnesso","Response":"1. Wine","Prediction":["Wine"]}
{"Individual":"Medium","Response":"1. WineBody\n2. Wine","Prediction":["WineBody","Wine"]}
{"Individual":"MedocRegion","Response":"1. Bordeaux\n2. Region","Prediction":["Bordeaux","Region"]}
{"Individual":"MendocinoRegion","Response":"1. Region\n2. RedTableWine","Prediction":["Region","RedTableWine"]}
{"Individual":"MeursaultRegion","Response":"1. Region\n2. WhiteBurgundy","Prediction":["Region","WhiteBurgundy"]}
{"Individual":"Moderate","Response":"1. WineBody\n2. Wine\n3. PotableLiquid","Prediction":["WineBody","Wine","PotableLiquid"]}
{"Individual":"MountEdenVineyard","Response":"1. Winery\n2. Wine\n3. WineGrape","Prediction":["Winery","Wine","WineGrape"]}
{"Individual":"MountEdenVineyardEdnaValleyChardonnay","Response":"1. Chardonnay\n2. Wine\n3. WhiteWine\n4. WineBody","Prediction":["Chardonnay","Wine","WhiteWine","WineBody"]}
{"Individual":"MountEdenVineyardEstatePinotNoir","Response":"1. PinotNoir\n2. Wine\n3. RedWine","Prediction":["PinotNoir","Wine","RedWine"]}
{"Individual":"Mountadam","Response":"1. Wine","Prediction":["Wine"]}
{"Individual":"MountadamChardonnay","Response":"1. Chardonnay\n2. Wine","Prediction":["Chardonnay","Wine"]}
{"Individual":"MountadamPinotNoir","Response":"1. PinotNoir\n2. Wine\n3. RedTableWine","Prediction":["PinotNoir","Wine","RedTableWine"]}
{"Individual":"MountadamRiesling","Response":"1. Riesling\n2. DryRiesling\n3. WhiteWine\n4. Wine","Prediction":["Riesling","DryRiesling","WhiteWine","Wine"]}
{"Individual":"MuscadetRegion","Response":"1. Region","Prediction":["Region"]}
{"Individual":"NapaRegion","Response":"1. Region","Prediction":["Region"]}
{"Individual":"NewZealandRegion","Response":"1. Region","Prediction":["Region"]}
{"Individual":"OffDry","Response":"1. LateHarvest\n2. SweetRiesling","Prediction":["LateHarvest","SweetRiesling"]}
{"Individual":"PageMillWinery","Response":"1. Winery\n2. Wine","Prediction":["Winery","Wine"]}
{"Individual":"PageMillWineryCabernetSauvignon","Response":"1. Winery\n2. Wine\n3. CabernetSauvignon\n4. Grape","Prediction":["Winery","Wine","CabernetSauvignon","Grape"]}
{"Individual":"PauillacRegion","Response":"1. Region\n2. Bordeaux","Prediction":["Region","Bordeaux"]}
{"Individual":"PeterMccoy","Response":"1. Winery","Prediction":["Winery"]}
{"Individual":"PeterMccoyChardonnay","Response":"1. Chardonnay\n2. Wine","Prediction":["Chardonnay","Wine"]}
{"Individual":"PetiteSyrahGrape","Response":"1. WineGrape\n2. Grape\n3. Syrah","Prediction":["WineGrape","Grape","Syrah"]}
{"Individual":"PetiteVerdotGrape","Response":"1. WineGrape\n2. Grape","Prediction":["WineGrape","Grape"]}
{"Individual":"PinotBlancGrape","Response":"1. WineGrape\n2. Grape","Prediction":["WineGrape","Grape"]}
{"Individual":"PinotNoirGrape","Response":"1. WineGrape\n2. Grape","Prediction":["WineGrape","Grape"]}
{"Individual":"PortugalRegion","Response":"1. Bordeaux\n2. Region","Prediction":["Bordeaux","Region"]}
{"Individual":"PulignyMontrachet","Response":"1. WhiteBurgundy\n2. Meursault","Prediction":["WhiteBurgundy","Meursault"]}
{"Individual":"PulignyMontrachetWhiteBurgundy","Response":"1. WhiteBurgundy\n2. Wine","Prediction":["WhiteBurgundy","Wine"]}
{"Individual":"Red","Response":"1. RedWine\n2. WineBody","Prediction":["RedWine","WineBody"]}
{"Individual":"RieslingGrape","Response":"1. WineGrape\n2. Grape\n3. Riesling","Prediction":["WineGrape","Grape","Riesling"]}
{"Individual":"Rose","Response":"1. Wine\n2. RedWine","Prediction":["Wine","RedWine"]}
{"Individual":"RoseDAnjou","Response":"1. Wine\n2. WineColor\n3. Anjou\n4. RedWine","Prediction":["Wine","WineColor","Anjou","RedWine"]}
{"Individual":"SancerreRegion","Response":"1. Region\n2. Sancerre","Prediction":["Region","Sancerre"]}
{"Individual":"SangioveseGrape","Response":"1. WineGrape\n2. Grape","Prediction":["WineGrape","Grape"]}
{"Individual":"SantaBarbaraRegion","Response":"1. Region","Prediction":["Region"]}
{"Individual":"SantaCruzMountainVineyard","Response":"1. Winery\n2. Region","Prediction":["Winery","Region"]}
{"Individual":"SantaCruzMountainVineyardCabernetSauvignon","Response":"1. CabernetSauvignon\n2. Wine\n3. RedWine","Prediction":["CabernetSauvignon","Wine","RedWine"]}
{"Individual":"SantaCruzMountainsRegion","Response":"1. Region","Prediction":["Region"]}
{"Individual":"SaucelitoCanyon","Response":"1. Wine\n2. Region\n3. WineGrape\n4. Grape","Prediction":["Wine","Region","WineGrape","Grape"]}
{"Individual":"SaucelitoCanyonZinfandel","Response":"1. Zinfandel\n2. RedWine\n3. Wine\n4. Meritage","Prediction":["Zinfandel","RedWine","Wine","Meritage"]}
{"Individual":"SaucelitoCanyonZinfandel1998","Response":"1. Zinfandel\n2. RedWine\n3. Wine\n4. Meritage","Prediction":["Zinfandel","RedWine","Wine","Meritage"]}
{"Individual":"SauterneRegion","Response":"1. Region\n2. Bordeaux","Prediction":["Region","Bordeaux"]}
{"Individual":"SauvignonBlancGrape","Response":"1. WineGrape\n2. Grape","Prediction":["WineGrape","Grape"]}
{"Individual":"SchlossRothermel","Response":"1. Chateau\n2. Bordeaux\n3. Winery","Prediction":["Chateau","Bordeaux","Winery"]}
{"Individual":"SchlossRothermelTrochenbierenausleseRiesling","Response":"1. DessertWine\n2. IceWine\n3. Riesling\n4. Wine","Prediction":["DessertWine","IceWine","Riesling","Wine"]}
{"Individual":"SchlossVolrad","Response":"1. Winery\n2. Wine\n3. RedWine","Prediction":["Winery","Wine","RedWine"]}
{"Individual":"SchlossVolradTrochenbierenausleseRiesling","Response":"1. DessertWine\n2. IceWine\n3. Riesling\n4. Wine","Prediction":["DessertWine","IceWine","Riesling","Wine"]}
{"Individual":"SeanThackrey","Response":"1. Winery\n2. Wine\n3. WineGrape\n4. Grape","Prediction":["Winery","Wine","WineGrape","Grape"]}
{"Individual":"SeanThackreySiriusPetiteSyrah","Response":"1. PetiteSyrah\n2. Wine\n3. Grape\n4. Syrah","Prediction":["PetiteSyrah","Wine","Grape","Syrah"]}
{"Individual":"Selaks","Response":"1. WineGrape","Prediction":["WineGrape"]}
{"Individual":"SelaksIceWine","Response":"1. IceWine\n2. Wine","Prediction":["IceWine","Wine"]}
{"Individual":"SelaksSauvignonBlanc","Response":"1. Sauvignon Blanc\n2. WineGrape\n3. Grape\n4. WhiteWine","Prediction":["Sauvignon","Blanc","WineGrape","Grape","WhiteWine"]}
{"Individual":"SemillonGrape","Response":"1. WineGrape\n2. Grape","Prediction":["WineGrape","Grape"]}
{"Individual":"SevreEtMaine","Response":"1. Bordeaux\n2. Region\n3. Wine\n4. WineGrape","Prediction":["Bordeaux","Region","Wine","WineGrape"]}
{"Individual":"SevreEtMaineMuscadet","Response":"1. Muscadet\n2. Wine","Prediction":["Muscadet","Wine"]}
{"Individual":"SonomaRegion","Response":"1. Region","Prediction":["Region"]}
{"Individual":"SouthAustraliaRegion","Response":"1. Region","Prediction":["Region"]}
{"Individual":"StEmilionRegion","Response":"1. Region\n2. StEmilion","Prediction":["Region","StEmilion"]}
{"Individual":"StGenevieve","Response":"1. Meritage\n2. Bordeaux","Prediction":["Meritage","Bordeaux"]}
{"Individual":"StGenevieveTexasWhite","Response":"1. WhiteWine\n2. Wine\n3. Grape\n4. Region","Prediction":["WhiteWine","Wine","Grape","Region"]}
{"Individual":"Stonleigh","Response":"1. Winery","Prediction":["Winery"]}
{"Individual":"StonleighSauvignonBlanc","Response":"1. SauvignonBlanc\n2. Wine","Prediction":["SauvignonBlanc","Wine"]}
{"Individual":"Strong","Response":"1. WineBody","Prediction":["WineBody"]}
{"Individual":"Sweet","Response":"1. WineSugar\n2. DessertWine\n3. SweetRiesling","Prediction":["WineSugar","DessertWine","SweetRiesling"]}
{"Individual":"Taylor","Response":"1. Chardonnay","Prediction":["Chardonnay"]}
{"Individual":"TaylorPort","Response":"1. DessertWine\n2. Port","Prediction":["DessertWine","Port"]}
{"Individual":"TexasRegion","Response":"1. Region","Prediction":["Region"]}
{"Individual":"ToursRegion","Response":"1. Region","Prediction":["Region"]}
{"Individual":"USRegion","Response":"1. Region","Prediction":["Region"]}
{"Individual":"Ventana","Response":"1. Winery","Prediction":["Winery"]}
{"Individual":"VentanaCheninBlanc","Response":"1. WhiteWine\n2. Wine\n3. CheninBlanc\n4. Chardonnay","Prediction":["WhiteWine","Wine","CheninBlanc","Chardonnay"]}
{"Individual":"White","Response":"1. WhiteWine\n2. WineColor","Prediction":["WhiteWine","WineColor"]}
{"Individual":"WhitehallLane","Response":"1. Winery","Prediction":["Winery"]}
{"Individual":"WhitehallLaneCabernetFranc","Response":"1. Meritage\n2. CabernetFranc\n3. Wine\n4. RedTableWine","Prediction":["Meritage","CabernetFranc","Wine","RedTableWine"]}
{"Individual":"WhitehallLanePrimavera","Response":"1. Chardonnay\n2. WhiteWine\n3. Wine\n4. WineBody","Prediction":["Chardonnay","WhiteWine","Wine","WineBody"]}
{"Individual":"Year1998","Response":"1. VintageYear","Prediction":["VintageYear"]}
{"Individual":"ZinfandelGrape","Response":"1. WineGrape\n2. Grape\n3. Zinfandel","Prediction":["WineGrape","Grape","Zinfandel"]}
